aileen/manage.py
aileen-0.2.1.dist-info/LICENSE
aileen-0.2.1.dist-info/METADATA
aileen-0.2.1.dist-info/WHEEL
aileen-0.2.1.dist-info/top_level.txt
aileen-0.2.1.dist-info/RECORD
