Metadata-Version: 2.1
Name: aileen
Version: 0.2.1
Summary: The Aileen project - A data-driven service layer for Humanitarian Aid
Home-page: UNKNOWN
Author: Seita BV, PNGK BV
Author-email: nicolas@seita.nl
License: UNKNOWN
Platform: UNKNOWN
Classifier: Programming Language :: Python
Classifier: Programming Language :: Python :: 3
Classifier: Development Status :: 3 - Alpha
Classifier: Operating System :: OS Independent
Requires-Dist: black
Requires-Dist: Click
Requires-Dist: django (==1.11.16)
Requires-Dist: django-bootstrap3
Requires-Dist: django-geojson
Requires-Dist: django-leaflet
Requires-Dist: django-pandas
Requires-Dist: humanize
Requires-Dist: libtmux
Requires-Dist: netifaces
Requires-Dist: numpy
Requires-Dist: pandas
Requires-Dist: pexpect
Requires-Dist: pytz
Requires-Dist: requests
